{
  "$schema": "https://vega.github.io/schema/vega-lite/v5.20.1.json",
  "config": {
    "background": "#030712",
    "view": {
      "stroke": "transparent"
    },
    "axis": {
      "labelColor": "#E0E0E0",
      "titleColor": "#FFFFFF",
      "gridColor": "#333333",
      "domainColor": "#444444",
      "tickColor": "#444444"
    },
    "legend": {
      "labelColor": "#E0E0E0",
      "titleColor": "#FFFFFF"
    },
    "title": {
      "color": "#FFFFFF"
    }
  },
  "data": {
    "name": "data-ce15d3fec6fa9bc3759b0fb92710e284"
  },
  "datasets": {
    "data-ce15d3fec6fa9bc3759b0fb92710e284": [
      {
        "Country": "AUS",
        "Efficacy_Gap": 0.3600957602605135,
        "Gender": "Female",
        "Math_Efficacy": -0.4308212037637898,
        "Math_Score": 484.8024089876704
      },
      {
        "Country": "AUS",
        "Efficacy_Gap": 0.3600957602605135,
        "Gender": "Male",
        "Math_Efficacy": -0.07072544350327634,
        "Math_Score": 499.50426418411377
      },
      {
        "Country": "BEL",
        "Efficacy_Gap": 0.29886321355961787,
        "Gender": "Female",
        "Math_Efficacy": -0.4509557946069994,
        "Math_Score": 496.81706769936886
      },
      {
        "Country": "BEL",
        "Efficacy_Gap": 0.29886321355961787,
        "Gender": "Male",
        "Math_Efficacy": -0.15209258104738155,
        "Math_Score": 510.93983759351624
      },
      {
        "Country": "BRA",
        "Efficacy_Gap": 0.29566373956095504,
        "Gender": "Female",
        "Math_Efficacy": -1.0041230106436898,
        "Math_Score": 383.8422448048657
      },
      {
        "Country": "BRA",
        "Efficacy_Gap": 0.29566373956095504,
        "Gender": "Male",
        "Math_Efficacy": -0.7084592710827348,
        "Math_Score": 395.91332615057195
      },
      {
        "Country": "CHE",
        "Efficacy_Gap": 0.3671996551864994,
        "Gender": "Female",
        "Math_Efficacy": -0.17961037593984963,
        "Math_Score": 509.0357007518797
      },
      {
        "Country": "CHE",
        "Efficacy_Gap": 0.3671996551864994,
        "Gender": "Male",
        "Math_Efficacy": 0.18758927924664975,
        "Math_Score": 524.1984596160811
      },
      {
        "Country": "CHL",
        "Efficacy_Gap": 0.3728398026123927,
        "Gender": "Female",
        "Math_Efficacy": -0.7760578532946539,
        "Math_Score": 427.9246195607128
      },
      {
        "Country": "CHL",
        "Efficacy_Gap": 0.3728398026123927,
        "Gender": "Male",
        "Math_Efficacy": -0.40321805068226124,
        "Math_Score": 447.602440545809
      },
      {
        "Country": "CZE",
        "Efficacy_Gap": 0.3123306903895601,
        "Gender": "Female",
        "Math_Efficacy": -0.4602671261378414,
        "Math_Score": 500.56107074122235
      },
      {
        "Country": "CZE",
        "Efficacy_Gap": 0.3123306903895601,
        "Gender": "Male",
        "Math_Efficacy": -0.14793643574828133,
        "Math_Score": 508.25464040190377
      },
      {
        "Country": "DNK",
        "Efficacy_Gap": 0.45494654565099946,
        "Gender": "Female",
        "Math_Efficacy": -0.5946572123176661,
        "Math_Score": 478.1729108589951
      },
      {
        "Country": "DNK",
        "Efficacy_Gap": 0.45494654565099946,
        "Gender": "Male",
        "Math_Efficacy": -0.13971066666666668,
        "Math_Score": 489.7567380392157
      },
      {
        "Country": "FRA",
        "Efficacy_Gap": 0.31712922745956595,
        "Gender": "Female",
        "Math_Efficacy": -0.22293524305555554,
        "Math_Score": 475.29733263888886
      },
      {
        "Country": "FRA",
        "Efficacy_Gap": 0.31712922745956595,
        "Gender": "Male",
        "Math_Efficacy": 0.09419398440401039,
        "Math_Score": 489.9389736353509
      },
      {
        "Country": "GBR",
        "Efficacy_Gap": 0.3521241179475799,
        "Gender": "Female",
        "Math_Efficacy": -0.42358704563031707,
        "Math_Score": 482.60025251353443
      },
      {
        "Country": "GBR",
        "Efficacy_Gap": 0.3521241179475799,
        "Gender": "Male",
        "Math_Efficacy": -0.07146292768273717,
        "Math_Score": 498.00156706842927
      },
      {
        "Country": "HKG",
        "Efficacy_Gap": 0.40937982906285664,
        "Gender": "Female",
        "Math_Efficacy": -0.6571272962962963,
        "Math_Score": 541.7194274074074
      },
      {
        "Country": "HKG",
        "Efficacy_Gap": 0.40937982906285664,
        "Gender": "Male",
        "Math_Efficacy": -0.24774746723343963,
        "Math_Score": 552.9888278427205
      },
      {
        "Country": "HUN",
        "Efficacy_Gap": 0.31184331475249877,
        "Gender": "Female",
        "Math_Efficacy": -0.4091904508342208,
        "Math_Score": 476.88803372381966
      },
      {
        "Country": "HUN",
        "Efficacy_Gap": 0.31184331475249877,
        "Gender": "Male",
        "Math_Efficacy": -0.097347136081722,
        "Math_Score": 493.74254615103973
      },
      {
        "Country": "ISR",
        "Efficacy_Gap": 0.3388371189810245,
        "Gender": "Female",
        "Math_Efficacy": -0.7206423164024588,
        "Math_Score": 458.30956098350043
      },
      {
        "Country": "ISR",
        "Efficacy_Gap": 0.3388371189810245,
        "Gender": "Male",
        "Math_Efficacy": -0.3818051974214343,
        "Math_Score": 480.0848473005641
      },
      {
        "Country": "JPN",
        "Efficacy_Gap": 0.33137145882279856,
        "Gender": "Female",
        "Math_Efficacy": -0.6714412748171369,
        "Math_Score": 532.2649637756879
      },
      {
        "Country": "JPN",
        "Efficacy_Gap": 0.33137145882279856,
        "Gender": "Male",
        "Math_Efficacy": -0.34006981599433833,
        "Math_Score": 541.0827781316349
      },
      {
        "Country": "MAC",
        "Efficacy_Gap": 0.3516932893081761,
        "Gender": "Female",
        "Math_Efficacy": -0.28901080952380953,
        "Math_Score": 543.5710457142857
      },
      {
        "Country": "MAC",
        "Efficacy_Gap": 0.3516932893081761,
        "Gender": "Male",
        "Math_Efficacy": 0.06268247978436657,
        "Math_Score": 559.8049092542677
      },
      {
        "Country": "NLD",
        "Efficacy_Gap": 0.4938007165383815,
        "Gender": "Female",
        "Math_Efficacy": -0.5659860878145042,
        "Math_Score": 499.9914208189442
      },
      {
        "Country": "NLD",
        "Efficacy_Gap": 0.4938007165383815,
        "Gender": "Male",
        "Math_Efficacy": -0.07218537127612272,
        "Math_Score": 512.2416567363273
      },
      {
        "Country": "NOR",
        "Efficacy_Gap": 0.35772122055305544,
        "Gender": "Female",
        "Math_Efficacy": -0.6597946473779386,
        "Math_Score": 476.48540940325495
      },
      {
        "Country": "NOR",
        "Efficacy_Gap": 0.35772122055305544,
        "Gender": "Male",
        "Math_Efficacy": -0.30207342682488314,
        "Math_Score": 482.4631042790363
      },
      {
        "Country": "NZL",
        "Efficacy_Gap": 0.43228084618965523,
        "Gender": "Female",
        "Math_Efficacy": -0.624605695889054,
        "Math_Score": 479.7862550767707
      },
      {
        "Country": "NZL",
        "Efficacy_Gap": 0.43228084618965523,
        "Gender": "Male",
        "Math_Efficacy": -0.1923248496993988,
        "Math_Score": 497.89029609218437
      },
      {
        "Country": "POL",
        "Efficacy_Gap": 0.28217224031302274,
        "Gender": "Female",
        "Math_Efficacy": -0.7012684097421203,
        "Math_Score": 495.0690702005731
      },
      {
        "Country": "POL",
        "Efficacy_Gap": 0.28217224031302274,
        "Gender": "Male",
        "Math_Efficacy": -0.4190961694290976,
        "Math_Score": 506.444791160221
      },
      {
        "Country": "SVN",
        "Efficacy_Gap": 0.2925341683736296,
        "Gender": "Female",
        "Math_Efficacy": -0.5977496121416527,
        "Math_Score": 477.8163187183811
      },
      {
        "Country": "SVN",
        "Efficacy_Gap": 0.2925341683736296,
        "Gender": "Male",
        "Math_Efficacy": -0.30521544376802306,
        "Math_Score": 478.466507850048
      },
      {
        "Country": "SWE",
        "Efficacy_Gap": 0.281009687223859,
        "Gender": "Female",
        "Math_Efficacy": -0.43053551994036526,
        "Math_Score": 487.4985806932538
      },
      {
        "Country": "SWE",
        "Efficacy_Gap": 0.281009687223859,
        "Gender": "Male",
        "Math_Efficacy": -0.1495258327165063,
        "Math_Score": 494.56759178386375
      }
    ]
  },
  "hconcat": [
    {
      "encoding": {
        "color": {
          "field": "Gender",
          "legend": {
            "orient": "top",
            "title": "Gender"
          },
          "scale": {
            "domain": [
              "Female",
              "Male"
            ],
            "range": [
              "#E91E63",
              "#1976D2"
            ]
          },
          "type": "nominal"
        },
        "opacity": {
          "condition": {
            "param": "country_select",
            "value": 1
          },
          "value": 0.3
        },
        "tooltip": [
          {
            "field": "Country",
            "type": "nominal"
          },
          {
            "field": "Gender",
            "type": "nominal"
          },
          {
            "field": "Math_Efficacy",
            "format": ".2f",
            "title": "Confidence",
            "type": "quantitative"
          }
        ],
        "x": {
          "field": "Math_Efficacy",
          "scale": {
            "domain": [
              -1.0,
              0.6
            ]
          },
          "title": "Math Self-Efficacy (Confidence)",
          "type": "quantitative"
        },
        "xOffset": {
          "field": "Gender",
          "type": "nominal"
        },
        "y": {
          "field": "Country",
          "sort": {
            "field": "Efficacy_Gap",
            "order": "descending"
          },
          "title": null,
          "type": "nominal"
        }
      },
      "height": 350,
      "mark": {
        "cornerRadiusBottomRight": 4,
        "cornerRadiusTopRight": 4,
        "cursor": "pointer",
        "type": "bar"
      },
      "name": "view_1",
      "title": {
        "color": "#FFFFFF",
        "fontSize": 14,
        "text": "Click Country: Confidence Gap"
      },
      "width": 450
    },
    {
      "encoding": {
        "color": {
          "field": "Gender",
          "legend": {
            "orient": "top",
            "title": "Gender"
          },
          "scale": {
            "domain": [
              "Female",
              "Male"
            ],
            "range": [
              "#E91E63",
              "#1976D2"
            ]
          },
          "type": "nominal"
        },
        "tooltip": [
          {
            "field": "Country",
            "type": "nominal"
          },
          {
            "field": "Gender",
            "type": "nominal"
          },
          {
            "field": "Math_Score",
            "format": ".0f",
            "title": "Achievement",
            "type": "quantitative"
          }
        ],
        "x": {
          "field": "Math_Score",
          "scale": {
            "domain": [
              350,
              600
            ]
          },
          "title": "Actual Math Score (Achievement)",
          "type": "quantitative"
        },
        "y": {
          "field": "Gender",
          "title": null,
          "type": "nominal"
        }
      },
      "height": 350,
      "mark": {
        "cornerRadiusBottomRight": 4,
        "cornerRadiusTopRight": 4,
        "type": "bar"
      },
      "title": {
        "color": "#FFFFFF",
        "fontSize": 14,
        "text": "Achievement Gap for Selected Country"
      },
      "transform": [
        {
          "filter": {
            "param": "country_select"
          }
        }
      ],
      "width": 450
    }
  ],
  "params": [
    {
      "name": "country_select",
      "select": {
        "fields": [
          "Country"
        ],
        "type": "point"
      },
      "views": [
        "view_1"
      ]
    }
  ],
  "resolve": {
    "scale": {
      "color": "independent"
    }
  }
}